cheapodb/__init__.py
cheapodb/database.py
cheapodb/stream.py
cheapodb/table.py
cheapodb/utils.py
cheapodb-0.0.11.dist-info/LICENSE.md
cheapodb-0.0.11.dist-info/METADATA
cheapodb-0.0.11.dist-info/WHEEL
cheapodb-0.0.11.dist-info/top_level.txt
cheapodb-0.0.11.dist-info/RECORD
