Metadata-Version: 2.1
Name: cheapodb
Version: 0.0.11
Summary: Opinionated implementation of AWS Glue
Home-page: https://github.com/mineralzen/cheapodb
Author: Cole Howard
Author-email: cole.howard@mineralzen.com
License: MIT
Keywords: data,aws
Platform: UNKNOWN
Classifier: Development Status :: 2 - Pre-Alpha
Classifier: Intended Audience :: Developers
Classifier: Intended Audience :: End Users/Desktop
Classifier: License :: OSI Approved :: MIT License
Classifier: Operating System :: OS Independent
Classifier: Programming Language :: Python :: 3.6
Classifier: Programming Language :: Python :: 3.7
Requires-Dist: boto3 (==1.9.180)
Requires-Dist: PyAthena (==1.6.1)
Provides-Extra: pandas
Requires-Dist: pandas (>=0.24.0) ; extra == 'pandas'
